containerchecker/__init__.py
containerchecker/config.py
containerchecker/constants.py
containerchecker/containers.py
containerchecker/log_handler.py
containerchecker/main.py
containerchecker/ssh.py
containerchecker/version.py
python_containerchecker-1.0.0.dist-info/licenses/LICENSE
python_containerchecker-1.0.0.dist-info/METADATA
python_containerchecker-1.0.0.dist-info/WHEEL
python_containerchecker-1.0.0.dist-info/entry_points.txt
python_containerchecker-1.0.0.dist-info/top_level.txt
python_containerchecker-1.0.0.dist-info/RECORD
