Metadata-Version: 2.4
Name: python-containerchecker
Version: 1.0.0
Author-email: Tim Bryant <timothybryant3@gmail.com>
Requires-Python: >=3.11
License-File: LICENSE
Requires-Dist: paramiko
Requires-Dist: PyYAML
Requires-Dist: rich
Provides-Extra: dev
Requires-Dist: pre-commit; extra == "dev"
Requires-Dist: pytest; extra == "dev"
Requires-Dist: python-semantic-release; extra == "dev"
Requires-Dist: black; extra == "dev"
Dynamic: license-file
